holy_cli/__init__.py
holy_cli/config.py
holy_cli/exceptions.py
holy_cli/log.py
holy_cli/cli/__init__.py
holy_cli/cli/global_commands.py
holy_cli/cli/server_commands.py
holy_cli/cloud/__init__.py
holy_cli/cloud/options.py
holy_cli/cloud/aws/__init__.py
holy_cli/cloud/aws/actions.py
holy_cli/cloud/aws/base.py
holy_cli/cloud/aws/iam.py
holy_cli/cloud/aws/image.py
holy_cli/cloud/aws/instance.py
holy_cli/cloud/aws/key_pair.py
holy_cli/cloud/aws/security_group.py
holy_cli/cloud/aws/ssh.py
holy_cli/cloud/aws/vpc.py
holy_cli/util/__init__.py
holy_cli/util/hash.py
holy_cli/util/names.py
holy_cli/util/version_check.py
holy_cli-1.0.2.dist-info/LICENSE.txt
holy_cli-1.0.2.dist-info/METADATA
holy_cli-1.0.2.dist-info/WHEEL
holy_cli-1.0.2.dist-info/entry_points.txt
holy_cli-1.0.2.dist-info/top_level.txt
holy_cli-1.0.2.dist-info/RECORD
