Metadata-Version: 2.1
Name: holy-cli
Version: 1.0.2
Summary: Holy is a CLI tool that makes it effortless to create, manage and connect to servers in your AWS account
Author-email: Holy <holy.cli.email@gmail.com>
License: MIT License
Project-URL: Homepage, https://github.com/holy-cli/cli
Project-URL: Bug Tracker, https://github.com/holy-cli/cli/issues
Keywords: aws,cloud,server,cli,holy,development,instance,ec2
Classifier: Intended Audience :: Developers
Classifier: Programming Language :: Python :: 3.9
Classifier: Programming Language :: Python :: 3.10
Classifier: Programming Language :: Python :: 3.11
Classifier: Programming Language :: Python :: 3.12
Classifier: License :: OSI Approved :: MIT License
Requires-Python: >=3.9
License-File: LICENSE.txt
Requires-Dist: click >=8.1
Requires-Dist: boto3 >=1.28
Requires-Dist: boto3-stubs[ec2,iam,ssm] >=1.28
Requires-Dist: yaspin >=2.5
Requires-Dist: tabulate >=0.9
Provides-Extra: tests
Requires-Dist: pytest ; extra == 'tests'
